oslo_cache/__init__.py
oslo_cache/_bmemcache_pool.py
oslo_cache/_i18n.py
oslo_cache/_memcache_pool.py
oslo_cache/_opts.py
oslo_cache/core.py
oslo_cache/exception.py
oslo_cache/testing.py
oslo_cache/version.py
oslo_cache/backends/__init__.py
oslo_cache/backends/dictionary.py
oslo_cache/backends/etcd3gw.py
oslo_cache/backends/memcache_pool.py
oslo_cache/backends/mongo.py
oslo_cache/locale/de/LC_MESSAGES/oslo_cache.po
oslo_cache/locale/en_GB/LC_MESSAGES/oslo_cache.po
oslo_cache/locale/es/LC_MESSAGES/oslo_cache.po
oslo_cache/locale/fr/LC_MESSAGES/oslo_cache.po
oslo_cache/locale/it/LC_MESSAGES/oslo_cache.po
oslo_cache/locale/ko_KR/LC_MESSAGES/oslo_cache.po
oslo_cache/locale/pt_BR/LC_MESSAGES/oslo_cache.po
oslo_cache/locale/ru/LC_MESSAGES/oslo_cache.po
oslo_cache/locale/tr_TR/LC_MESSAGES/oslo_cache.po
oslo_cache/locale/zh_CN/LC_MESSAGES/oslo_cache.po
oslo_cache/locale/zh_TW/LC_MESSAGES/oslo_cache.po
oslo_cache/tests/__init__.py
oslo_cache/tests/test_cache.py
oslo_cache/tests/functional/__init__.py
oslo_cache/tests/functional/test_base.py
oslo_cache/tests/functional/dogpile_cache_bmemcached/__init__.py
oslo_cache/tests/functional/dogpile_cache_bmemcached/test_cache_backend.py
oslo_cache/tests/functional/dogpile_cache_pymemcache/__init__.py
oslo_cache/tests/functional/dogpile_cache_pymemcache/test_cache_backend.py
oslo_cache/tests/functional/dogpile_cache_redis/__init__.py
oslo_cache/tests/functional/dogpile_cache_redis/test_cache_backend.py
oslo_cache/tests/functional/dogpile_cache_redis_sentinel/__init__.py
oslo_cache/tests/functional/dogpile_cache_redis_sentinel/test_cache_backend.py
oslo_cache/tests/functional/etcd3gw/__init__.py
oslo_cache/tests/functional/etcd3gw/test_cache_backend.py
oslo_cache/tests/functional/memcache_pool/__init__.py
oslo_cache/tests/functional/memcache_pool/test_cache_backend.py
oslo_cache/tests/unit/__init__.py
oslo_cache/tests/unit/test_cache_backend_mongo.py
oslo_cache/tests/unit/test_cache_basics.py
oslo_cache-3.11.0.dist-info/AUTHORS
oslo_cache-3.11.0.dist-info/LICENSE
oslo_cache-3.11.0.dist-info/METADATA
oslo_cache-3.11.0.dist-info/WHEEL
oslo_cache-3.11.0.dist-info/entry_points.txt
oslo_cache-3.11.0.dist-info/pbr.json
oslo_cache-3.11.0.dist-info/top_level.txt
oslo_cache-3.11.0.dist-info/RECORD
