Metadata-Version: 2.1
Name: oslo.cache
Version: 3.11.0
Summary: Cache storage for OpenStack projects.
Home-page: https://docs.openstack.org/oslo.cache/latest
Author: OpenStack
Author-email: openstack-discuss@lists.openstack.org
Classifier: Environment :: OpenStack
Classifier: Intended Audience :: Information Technology
Classifier: Intended Audience :: System Administrators
Classifier: License :: OSI Approved :: Apache Software License
Classifier: Operating System :: POSIX :: Linux
Classifier: Programming Language :: Python
Classifier: Programming Language :: Python :: 3 :: Only
Classifier: Programming Language :: Python :: 3
Classifier: Programming Language :: Python :: 3.9
Classifier: Programming Language :: Python :: 3.10
Classifier: Programming Language :: Python :: 3.11
Classifier: Programming Language :: Python :: 3.12
Requires-Python: >=3.9
License-File: LICENSE
Requires-Dist: dogpile.cache>=1.3.3
Requires-Dist: oslo.config>=8.1.0
Requires-Dist: oslo.i18n>=5.0.0
Requires-Dist: oslo.log>=4.2.1
Requires-Dist: oslo.utils>=4.2.0
Requires-Dist: debtcollector>=3.0.0
Provides-Extra: dogpile
Requires-Dist: python-memcached>=1.56; extra == "dogpile"
Requires-Dist: pymemcache>=3.5.0; extra == "dogpile"
Requires-Dist: python-binary-memcached>=0.29.0; extra == "dogpile"
Requires-Dist: redis>=3.0.0; extra == "dogpile"
Provides-Extra: mongo
Requires-Dist: pymongo>=3.0.2; extra == "mongo"
Provides-Extra: etcd3gw
Requires-Dist: etcd3gw>=0.2.0; extra == "etcd3gw"
Provides-Extra: test
Requires-Dist: oslotest>=3.2.0; extra == "test"
Requires-Dist: pifpaf>=0.10.0; extra == "test"
Requires-Dist: stestr>=2.0.0; extra == "test"
Requires-Dist: pymemcache>=3.5.0; extra == "test"
Requires-Dist: python-binary-memcached>=0.29.0; extra == "test"
Requires-Dist: python-memcached>=1.56; extra == "test"
Requires-Dist: pymongo>=3.0.2; extra == "test"
Requires-Dist: etcd3gw>=0.2.0; extra == "test"
Requires-Dist: redis>=3.0.0; extra == "test"
